ml_commons/__init__.py
ml_commons/layers/__init__.py
ml_commons/layers/channelwise_dense/__init__.py
ml_commons/layers/channelwise_dense/channelwise_dense.py
ml_commons/layers/unpool/__init__.py
ml_commons/layers/unpool/unpool.py
ml_commons/utils/__init__.py
ml_commons/utils/early_stopping/__init__.py
ml_commons/utils/early_stopping/early_stopping.py
ml_commons_pekalam-0.0.1.dev2.dist-info/LICENSE
ml_commons_pekalam-0.0.1.dev2.dist-info/METADATA
ml_commons_pekalam-0.0.1.dev2.dist-info/WHEEL
ml_commons_pekalam-0.0.1.dev2.dist-info/top_level.txt
ml_commons_pekalam-0.0.1.dev2.dist-info/RECORD
