Metadata-Version: 2.1
Name: ml-commons-pekalam
Version: 0.0.1.dev2
Summary: Tensorflow utilities and custom implementations used in my projects.
Home-page: UNKNOWN
Author: Marek Pękala
License: UNKNOWN
Platform: UNKNOWN
Classifier: Programming Language :: Python :: 3
Classifier: License :: OSI Approved :: MIT License
Classifier: Operating System :: OS Independent
Requires-Python: >=3.6
License-File: LICENSE
